requirements.txt
setup.py
django_schedule_daemon/__init__.py
django_schedule_daemon.egg-info/PKG-INFO
django_schedule_daemon.egg-info/SOURCES.txt
django_schedule_daemon.egg-info/dependency_links.txt
django_schedule_daemon.egg-info/requires.txt
django_schedule_daemon.egg-info/top_level.txt
django_schedule_daemon/management/__init__.py
django_schedule_daemon/management/commands/__init__.py
django_schedule_daemon/management/commands/schedule_daemon.py