Metadata-Version: 2.1
Name: django-schedule-daemon
Version: 2020.7.1
Summary: Django schedule daemon https://pypi.org/project/schedule/
Home-page: https://github.com/andrewp-as-is/django-schedule-daemon.py
License: Unlicense
Keywords: Django schedule daemon
Platform: UNKNOWN
Classifier: Framework :: Django
Classifier: License :: Public Domain
Classifier: Operating System :: OS Independent
Classifier: Programming Language :: Python :: 3
